{
  "bookCn": "创世记",
  "bookKey": "genesis",
  "chapter": 8,
  "title": "创世记8章",
  "theme": "神记念挪亚，逐步止息洪水，带领生命重新开始；挪亚则以顺服、等候和敬拜回应神。",
  "repeatedWords": [
    {
      "word": "地",
      "count": 12
    },
    {
      "word": "水",
      "count": 11
    },
    {
      "word": "方舟",
      "count": 8
    },
    {
      "word": "鸽子",
      "count": 6
    },
    {
      "word": "挪亚",
      "count": 6
    },
    {
      "word": "七天",
      "count": 2
    }
  ],
  "segments": [
    {
      "title": "1. 神记念，洪水开始退去（1-5节）",
      "rangeStart": 1,
      "rangeEnd": 5,
      "questions": [
        "第1节一开始说“神记念挪亚”，这句话在整段里起了什么作用？",
        "1到5节怎样一步步描写洪水退去的过程？哪些词让你感受到这不是瞬间完成的？",
        "方舟停在亚拉腊山上、山顶显出来，这些细节对方舟里的人意味着什么？"
      ]
    },
    {
      "title": "2. 挪亚不断察看，也不断等候（6-12节）",
      "rangeStart": 6,
      "rangeEnd": 12,
      "questions": [
        "挪亚先后放出乌鸦和鸽子，这两个行动各反映出他在关注什么？",
        "鸽子第一次回来、第二次叼回橄榄叶、第三次不再回来，这三个结果让局势有了怎样的推进？",
        "经文两次提到“又等了七天”，从挪亚的做法里你看到一种怎样的节奏：急着行动，还是谨慎等候？",
        "如果你身在方舟里，看到这些迹象时，最想立刻做什么？为什么挪亚似乎没有马上出去？"
      ]
    },
    {
      "title": "3. 地干了，但挪亚等神开口（13-19节）",
      "rangeStart": 13,
      "rangeEnd": 19,
      "questions": [
        "13到14节已经说地干了，为什么15到17节还特别记下神对挪亚说“可以出方舟”？",
        "神吩咐谁一同出方舟？又特别强调活物出去以后要做什么？",
        "18到19节里，挪亚一家和各类活物都出来了，这一幕让你想到“新的开始”有哪些具体画面？"
      ]
    },
    {
      "title": "4. 新开始先从敬拜开始（20-22节）",
      "rangeStart": 20,
      "rangeEnd": 22,
      "questions": [
        "挪亚出方舟后做的第一件事是筑坛献祭，这个次序说明他最看重什么？",
        "21节里，神一方面指出人心仍有恶念，另一方面又应许不再像之前那样毁灭活物；这让你看见神怎样对待仍不完全的人？",
        "22节提到稼穑、寒暑、冬夏、昼夜不停息，这个应许对经历过洪水的人会带来怎样的安稳？",
        "读完整章，你觉得“重新开始”最需要的，不只是环境改变，还包括什么？"
      ]
    }
  ],
  "closing": "创世记8章让人看见，神在记念中施行拯救，人则在等候中学习顺服，并以敬拜迎接新的开始。",
  "generatedAt": "2026-03-29T13:03:05.628Z",
  "version": "genesis-offline-v5"
}