{
  "version": "default",
  "versionLabel": "默认版",
  "contentLang": "zh",
  "bookId": "2CH",
  "bookLabel": "历代志下",
  "chapter": 25,
  "theme": "从亚玛谢的一生看见：人可以有好的开始，却因心不专诚、得胜后骄傲、拒绝劝戒而一步步远离神。",
  "repeatedWords": [
    {
      "word": "亚玛谢",
      "count": 14
    },
    {
      "word": "耶和华",
      "count": 8
    },
    {
      "word": "神",
      "count": 8
    },
    {
      "word": "以色列",
      "count": 9
    },
    {
      "word": "犹大",
      "count": 10
    },
    {
      "word": "王",
      "count": 15
    }
  ],
  "segments": [
    {
      "title": "好的开始，却显出心不专诚",
      "rangeStart": 1,
      "rangeEnd": 4,
      "questions": [
        "第2节说亚玛谢“行耶和华眼中看为正的事，只是心不专诚”，这句话怎样定下了他整章的属灵状态？",
        "亚玛谢在第3-4节处理父王被杀一事时，哪些做法是合乎律法的？这说明他对神的话有怎样的认识？",
        "从“做对一些事”到“心不专诚”，你觉得这两者之间有什么张力？经文让我们留意什么危险？"
      ]
    },
    {
      "title": "出征前的选择：靠人还是听神",
      "rangeStart": 5,
      "rangeEnd": 10,
      "questions": [
        "亚玛谢已经有三十万精兵，为什么还要花银子从以色列招募十万勇士？这反映了他想靠什么得胜？",
        "神人为什么明确反对以色列军兵同行？第7-8节怎样强调胜败的关键不在兵力？",
        "亚玛谢最先担心的是那一百他连得银子，第9节神人的回答指出了什么更重要的信心功课？",
        "第10节那些被遣回的军兵“甚恼怒”，亚玛谢顺服神的决定立刻带来了什么现实代价？"
      ]
    },
    {
      "title": "打了胜仗，却开始走偏",
      "rangeStart": 11,
      "rangeEnd": 16,
      "questions": [
        "第11节说亚玛谢“壮起胆来”，后来也确实打败了西珥人。这个胜利本来应该怎样帮助他更信靠神？",
        "第12-13节一边是犹大得胜，一边是被遣回的军兵攻击犹大各城。经文是否让我们看见：顺服神不等于一路没有损失？",
        "最令人意外的是第14节：亚玛谢竟把战败之民的神像带回敬拜。你觉得这暴露了他内心怎样的混乱和愚昧？",
        "面对先知责备，亚玛谢的反应是什么？第16节怎样显示，一个人拒绝劝戒时，问题已经不只是行为，而是心已经刚硬？"
      ]
    },
    {
      "title": "骄傲引战，神任凭他受败",
      "rangeStart": 17,
      "rangeEnd": 20,
      "questions": [
        "亚玛谢为什么会主动向以色列王约阿施挑战？第19节对他动机的分析，抓住了哪一个核心问题？",
        "约阿施用“蒺藜和香柏树”的比喻，是怎样讽刺亚玛谢高估自己、因小胜而自大的？",
        "第20节说亚玛谢“不肯听从”，而且“这是出乎神”。这节经文怎样把人的顽梗和神的审判连在一起？"
      ]
    },
    {
      "title": "败亡的结果与晚年的结局",
      "rangeStart": 21,
      "rangeEnd": 28,
      "questions": [
        "21-24节里，亚玛谢和犹大经历了哪些具体羞辱和损失？这些结果和他前面的选择有什么呼应？",
        "第27节特别说“自从亚玛谢离弃耶和华之后”，这句话怎样总结他人生转折点，也解释他后来被背叛、被杀的原因？",
        "从亚玛谢一生的结尾回头看，什么比外在的军事胜负更决定一个王的兴衰？这对今天的信仰生活有什么提醒？"
      ]
    }
  ],
  "chapterLeaderHint": [
    "带领时可以先请大家观察：本章不是单纯讲一场战争，而是在讲亚玛谢如何一步步偏离神。",
    "可以引导组员留意几个转折：听从神人、打胜仗、敬拜偶像、拒绝先知、主动挑衅、最终败亡。",
    "讨论时不要急着下结论，可先问：亚玛谢在哪些地方看起来还不错？又是从哪里开始明显走偏？",
    "本章很适合讨论“心不专诚”在现实中会怎么表现：表面守规矩、关键时刻靠人、得胜后骄傲、听不进提醒。",
    "应用时可轻轻落在：人最危险的时候不一定是失败时，也可能是在顺利、得胜、自我感觉良好的时候。",
    "若时间有限，可重点查考第2节、第9节、第14-16节、第19-20节、第27节，这几处最能串起全章。"
  ],
  "closing": "亚玛谢的故事提醒人：好的开始不等于好的结局。一个人若心不专诚，就可能在顺服中过于计较，在得胜后转向偶像，在被提醒时拒绝悔改。愿我们不只做一些对的事，也求神保守我们的心始终向他诚实、谦卑、肯受教。",
  "title": "历代志下25章查经：起初正直，却渐渐偏离",
  "generatedAt": "2026-03-31T11:39:16.318Z",
  "savedAt": "2026-03-31T11:39:16.318Z"
}