{
  "version": "default",
  "versionLabel": "默认版",
  "contentLang": "zh",
  "bookId": "LEV",
  "bookLabel": "利未记",
  "chapter": 13,
  "theme": "祭司如何分辨洁净与不洁净，并处理人和物上的灾病",
  "repeatedWords": [
    {
      "word": "祭司",
      "count": 49
    },
    {
      "word": "察看",
      "count": 30
    },
    {
      "word": "不洁净",
      "count": 22
    },
    {
      "word": "洁净",
      "count": 16
    },
    {
      "word": "关锁七天",
      "count": 8
    },
    {
      "word": "发散",
      "count": 14
    },
    {
      "word": "灾病",
      "count": 38
    }
  ],
  "segments": [
    {
      "title": "皮肤初步症状的检查与隔离",
      "rangeStart": 1,
      "rangeEnd": 8,
      "questions": [
        "1-3节里，祭司判断“大痲疯灾病”的依据有哪些外在迹象？这些标准说明判断不是靠感觉，而是靠什么？",
        "4-6节中，为什么当情况不明显时，不是马上定论，而是先关锁七天、再观察？这让你看到律法中的什么特点？",
        "7-8节提到，已经查过的人如果后来又“发散”了，还要再来见祭司。这里为什么特别重视“后续变化”？"
      ]
    },
    {
      "title": "旧患、全身变白与红肉显露",
      "rangeStart": 9,
      "rangeEnd": 17,
      "questions": [
        "9-11节中，什么情况一看就可以直接定为不洁净，不必再关锁？这和前一段有什么不同？",
        "12-13节说全身都变白反而定为洁净，这个判断看起来有些反常。经文中真正被注意的关键是什么？",
        "14-17节为什么一旦出现“红肉”就算不洁净，而红肉复原变白后又可以定为洁净？这里反映出祭司在观察什么变化？"
      ]
    },
    {
      "title": "疮后的灾病辨别",
      "rangeStart": 18,
      "rangeEnd": 23,
      "questions": [
        "18-20节中，原本已经治好的疮，如果后来又起变化，祭司要看哪些具体征象？",
        "21-23节里，怎样区分这是“大痲疯的灾病”还是只是“疮的痕迹”？经文特别强调了哪些观察点？"
      ]
    },
    {
      "title": "烧伤后的灾病辨别",
      "rangeStart": 24,
      "rangeEnd": 28,
      "questions": [
        "24-25节把火毒后的火斑也纳入检查，这说明律法对身体异常状况的处理有什么特点？",
        "26-28节中，祭司如何根据“有没有发散”“是否发暗”来作出判断？这些步骤和前面对疮的处理有何相似？"
      ]
    },
    {
      "title": "头上和胡须上的灾病",
      "rangeStart": 29,
      "rangeEnd": 37,
      "questions": [
        "29-30节里，头上或胡须上的灾病为什么要特别看“现象深于皮”和“细黄毛”？",
        "31-34节中，那人为什么可以剃去须发，却不可剃灾病之处？这对持续观察有什么帮助？",
        "35-37节让我们看到，得洁净之后若又发散，仍要重新检查。这里如何体现洁净判断不是一次性的结论？"
      ]
    },
    {
      "title": "白火斑与秃头的区分",
      "rangeStart": 38,
      "rangeEnd": 44,
      "questions": [
        "38-39节怎样区分“白癣”和真正的不洁净灾病？这对避免误判有什么意义？",
        "40-41节先说明头秃、顶门秃本身是洁净的。为什么经文要特别把正常现象和灾病分开？",
        "42-44节中，头秃处若出现什么迹象，就表明已经不是普通掉发，而是灾病？"
      ]
    },
    {
      "title": "不洁净者在群体中的状态",
      "rangeStart": 45,
      "rangeEnd": 46,
      "questions": [
        "45节要求患者撕裂衣服、蓬头散发、蒙着上唇并公开喊“不洁净了”，这些动作传达了什么信息？",
        "46节说他要独居营外。这样的安排对群体和对当事人分别意味着什么？"
      ]
    },
    {
      "title": "衣物上的灾病与第一次处理",
      "rangeStart": 47,
      "rangeEnd": 52,
      "questions": [
        "47-49节中，为什么连衣服、皮子这类物件也要交给祭司察看？这让你看到“洁净/不洁净”观念涵盖到什么范围？",
        "50-52节里，如果灾病在物件上发散，最后要怎样处理？经文为什么处理得这么彻底？"
      ]
    },
    {
      "title": "衣物上的灾病与后续复查",
      "rangeStart": 53,
      "rangeEnd": 59,
      "questions": [
        "53-56节中，对于没有发散的物件，祭司先吩咐清洗、再关锁、再复查。这个流程反映了怎样的谨慎？",
        "57-58节里，什么时候必须焚烧，什么时候可以再洗后算为洁净？判断的关键分别是什么？",
        "59节作为总结，整章反复说明“可以定为洁净或是不洁净”。你觉得本章最突出的重点是在治疗，还是在分辨？为什么？"
      ]
    }
  ],
  "chapterLeaderHint": [
    "这章内容较长，也有不少重复格式，带领时可以先提醒组员注意反复出现的词，如“祭司”“察看”“发散”“洁净”“不洁净”。",
    "可先请大家观察：本章最常见的流程是什么？通常是带到祭司面前、察看、必要时关锁七天、再复查、最后宣告。",
    "讨论时不要急着把“大痲疯”直接等同现代某一种疾病，重点先放在经文中的“分辨与宣告”功能。",
    "可引导组员比较不同案例：皮肤、疮、火毒、头疥、白火斑、秃头、衣物。虽然对象不同，但判断原则有共通之处。",
    "45-46节气氛明显转重，适合停下来讨论：不洁净不仅是个人问题，也影响群体生活。",
    "应用时可以轻轻带到：人容易凭外表快速下判断，但这章反而让我们看到要耐心观察、谨慎分辨，不急着下结论。"
  ],
  "closing": "利未记13章虽然细致繁琐，却让人看到神看重群体中的圣洁秩序，也看重判断时的谨慎、公正和可核实。本章不是叫人凭印象贴标签，而是要求祭司反复察看、按事实分辨。查考结束时，可以一起想一想：我们面对复杂的人和事，是不是也愿意像经文所示那样，不草率、不轻忽，而是认真分辨。",
  "title": "利未记13章查经问题",
  "generatedAt": "2026-03-31T09:14:07.145Z",
  "savedAt": "2026-03-31T09:14:07.145Z"
}