{
  "version": "default",
  "versionLabel": "默认版",
  "contentLang": "zh",
  "bookId": "1SA",
  "bookLabel": "撒母耳记上",
  "chapter": 8,
  "theme": "当人的不满和现实压力出现时，以色列人选择像列国一样立王；本章让人看见，他们表面上是在解决治理问题，实质上却暴露了对神作王的不信任。",
  "repeatedWords": [
    {
      "word": "王",
      "count": 14
    },
    {
      "word": "治理",
      "count": 5
    },
    {
      "word": "立",
      "count": 4
    },
    {
      "word": "依从",
      "count": 3
    },
    {
      "word": "取",
      "count": 7
    },
    {
      "word": "像列国一样",
      "count": 2
    }
  ],
  "segments": [
    {
      "title": "士师传承出了问题，百姓提出立王要求",
      "rangeStart": 1,
      "rangeEnd": 5,
      "questions": [
        "第1-3节怎样描写撒母耳的处境和他两个儿子的表现？这些问题为什么会让百姓不安？",
        "第4-5节里，以色列长老提出立王的理由是什么？他们的话里哪些部分看起来合理，哪些地方已经显出偏差？",
        "百姓说“像列国一样”，这句话在本段中透露出他们真正想要的是什么？"
      ]
    },
    {
      "title": "神指出问题核心：不是弃绝撒母耳，乃是弃绝神",
      "rangeStart": 6,
      "rangeEnd": 9,
      "questions": [
        "撒母耳听见百姓的要求后，第一反应是什么？这对处理教会或群体中的冲突有什么提醒？",
        "神在第7节怎样解释这件事的本质？为什么神说百姓不是厌弃撒母耳，而是厌弃祂自己？",
        "第8-9节把这次求王和以色列过去的历史连在一起，你看到这不是一次单独事件，而是一种怎样的属灵模式？",
        "神一面允许他们的要求，一面吩咐先警戒他们。这里让我们认识到神怎样对待人的坚持和选择？"
      ]
    },
    {
      "title": "撒母耳警告：王权会带来不断的索取",
      "rangeStart": 10,
      "rangeEnd": 18,
      "questions": [
        "第11-17节里，“必取”不断重复出现。这个重复让你对将来的王权产生什么整体印象？",
        "撒母耳提到王会取儿子、女儿、田地、粮食、仆婢和羊群。这里描绘的王，和百姓期待中“为我们争战”的王有什么反差？",
        "第18节说，到那时百姓哀求耶和华，耶和华却不应允。为什么到了那个时候，结果会这么严重？",
        "这段经文有没有提醒我们：人为了一个看似能解决问题的安排，可能会付上哪些原本没想到的代价？"
      ]
    },
    {
      "title": "百姓坚持己见，神准许他们走这条路",
      "rangeStart": 19,
      "rangeEnd": 22,
      "questions": [
        "面对撒母耳清楚的警告，百姓为什么还是坚持“不然！我们定要一个王”？他们最看重的到底是什么？",
        "第20节再次说“像列国一样”，并提到“统领我们，为我们争战”。这些期待反映出他们对安全感和领导的理解是什么？",
        "第21节里，撒母耳再次把百姓的话陈明在耶和华面前。这个细节怎样表现他处理事情的方式？",
        "神最后让撒母耳依从他们。结合全章来看，神的允许是否等于神的喜悦？这对我们分辨自己的坚持有什么帮助？"
      ]
    }
  ],
  "chapterLeaderHint": [
    "带领时可先请大家观察：本章里“王”“治理”“取”这些词反复出现，帮助组员先从经文本身进入主题。",
    "第一段讨论时，不要急着否定百姓，因为他们提出问题确实有现实背景；可先让大家分辨“合理担忧”和“错误方向”之间的差别。",
    "第二段可引导组员注意：神看问题比人更深，人看见的是制度危机，神指出的是关系危机和属灵拒绝。",
    "第三段适合让大家逐项观察王会“取”什么，帮助组员感受经文节奏中的压力，而不是只抽象讨论“立王对不对”。",
    "第四段可以追问：百姓为何在听完警告后仍坚持？帮助大家联系现实中人常常明知有风险，却仍想抓住看得见的依靠。",
    "应用时可轻轻带到生活：我们是否也常想要一个“立刻看得见、像周围人一样”的解决方案，却不愿继续信靠神的带领。",
    "若时间有限，可重点抓住两条线：一是百姓为何求王，二是神如何回应人的坚持。"
  ],
  "closing": "本章不是单纯讨论有没有王，而是在问：当人面对混乱、不安和未来压力时，到底要谁来作主？以色列人选择了看得见、像列国一样的保障，却忽略了真正的问题是他们不愿让耶和华继续作王。查经结束时，可以邀请大家安静想一想：我最近最想抓住的“王”是什么？",
  "title": "撒母耳记上第8章｜百姓求立王",
  "generatedAt": "2026-03-31T10:27:43.481Z",
  "savedAt": "2026-03-31T10:27:43.481Z"
}