{
  "default": {
    "zh": {
      "activeBuildId": "build_1774907380967_book_default_zh",
      "publishedAt": "2026-04-02T03:54:43.440Z",
      "publishMode": "merge",
      "lastMergedBuildId": "build_1774904368476_book_default_zh",
      "publishedCount": 56
    },
    "en": {
      "activeBuildId": ""
    },
    "es": {
      "activeBuildId": ""
    }
  },
  "children": {
    "zh": {
      "activeBuildId": "manual_children_zh",
      "publishedAt": "2026-04-02T03:54:07.622Z",
      "publishMode": "merge",
      "lastMergedBuildId": "build_1774945486639_book_children_zh",
      "publishedCount": 57
    }
  },
  "gospel": {
    "zh": {
      "publishMode": "merge",
      "lastMergedBuildId": "build_1775187802726_retry_job_1775021372720",
      "publishedAt": "2026-04-03T03:46:42.083Z",
      "publishedCount": 7
    }
  }
}