{
  "version": "default",
  "versionLabel": "默认版",
  "contentLang": "zh",
  "bookId": "GEN",
  "bookLabel": "创世记",
  "chapter": 6,
  "theme": "当世界普遍败坏、强暴满地时，神宣告审判；但在黑暗世代中，挪亚因与神同行而蒙恩，并以顺服回应神的吩咐。",
  "repeatedWords": [
    {
      "word": "败坏",
      "count": 4
    },
    {
      "word": "强暴",
      "count": 2
    },
    {
      "word": "凡有血气的",
      "count": 3
    },
    {
      "word": "挪亚",
      "count": 4
    },
    {
      "word": "方舟",
      "count": 5
    },
    {
      "word": "照样行",
      "count": 1
    }
  ],
  "segments": [
    {
      "title": "人的扩张与罪恶加深",
      "rangeStart": 1,
      "rangeEnd": 4,
      "questions": [
        "第1到4节怎样描写人越来越多之后的光景？经文特别把焦点放在哪些行为和结果上？",
        "第2节说“随意挑选，娶来为妻”，这句话让你看见人里面怎样的态度？",
        "第3节里，神提到“人既属乎血气”和“一百二十年”，这句话在这段紧张气氛中起了什么作用？"
      ]
    },
    {
      "title": "神看见人的罪恶并宣告除灭",
      "rangeStart": 5,
      "rangeEnd": 8,
      "questions": [
        "第5节怎样形容人的罪恶程度？从“终日所思想的尽都是恶”这句话，你看到问题已经深到哪里？",
        "第6到7节用了“后悔”“忧伤”“除灭”这些词，这些词怎样帮助我们理解神面对罪时的态度？",
        "在这样沉重的描述之后，第8节忽然说“惟有挪亚在耶和华眼前蒙恩”，这句话为什么特别关键？"
      ]
    },
    {
      "title": "挪亚与败坏世界形成对比",
      "rangeStart": 9,
      "rangeEnd": 12,
      "questions": [
        "第9节从哪几个方面介绍挪亚？“义人”“完全人”“与神同行”彼此之间有什么关系？",
        "第10节简短提到挪亚的三个儿子，这样的家庭信息放在这里，有什么铺垫作用？",
        "第11到12节两次提到世界“败坏”，又说“满了强暴”，这和前面挪亚的形象形成了什么鲜明对比？"
      ]
    },
    {
      "title": "神将审判计划告诉挪亚",
      "rangeStart": 13,
      "rangeEnd": 18,
      "questions": [
        "第13节里，神为什么要毁灭地上的活物？经文给出的原因是什么？",
        "第14到16节非常具体地描述方舟的材料、尺寸和结构，这些细节让你感受到神吩咐的什么特点？",
        "第17到18节一方面说洪水要毁灭天下，另一方面又说“我却要与你立约”，审判与保全在这里是怎样同时出现的？"
      ]
    },
    {
      "title": "保全生命的安排与挪亚的顺服",
      "rangeStart": 19,
      "rangeEnd": 22,
      "questions": [
        "第19到21节里，神对动物和食物都作了安排，这些安排反映出神怎样看待生命的延续？",
        "神要挪亚做的事既多又细，从这些吩咐看，挪亚需要怎样的信心和耐心？",
        "第22节只用一句话总结挪亚的回应：“凡神所吩咐的，他都照样行了。”这句话为什么是本章很重要的落点？"
      ]
    }
  ],
  "chapterLeaderHint": [
    "带领时可先请大家观察本章气氛的变化：从人的败坏，到神的忧伤与审判，再到挪亚蒙恩与顺服。",
    "第一段涉及一些较难解释的细节，如“神的儿子们”等，可先以经文观察为主，不必急着下结论，重点放在人类任意而行、罪恶加深。",
    "注意引导组员比较两条线：一条是全地越来越败坏，另一条是挪亚与神同行。这种对比是本章的重要结构。",
    "讨论神“后悔”“忧伤”时，可帮助大家从经文本身理解神不是冷漠的，祂真实地面对人的罪恶。",
    "查考方舟部分时，不妨请大家留意神吩咐的具体性，以及挪亚顺服的完整性，不只是有心愿，而是照着去行。",
    "应用时可轻轻带到：在混乱的环境中，一个人是否仍然愿意与神同行、按神的话去做。"
  ],
  "closing": "创世记第6章让人看见，罪恶不是表面的失控，而是人内里持续远离神，甚至全地都被败坏和强暴充满。但在这样的时代里，神仍看见一个与祂同行的人。愿我们读这章时，不只看见洪水前的黑暗，也看见挪亚那种安静而坚定的顺服。",
  "title": "创世记第6章：败坏中的审判与蒙恩之人",
  "generatedAt": "2026-03-31T08:25:38.313Z",
  "savedAt": "2026-03-31T08:25:38.313Z"
}