{
  "version": "default",
  "versionLabel": "默认版",
  "contentLang": "zh",
  "bookId": "EXO",
  "bookLabel": "出埃及记",
  "chapter": 11,
  "theme": "在最后审判临到之前，耶和华清楚宣告祂的计划，也显明祂怎样分别埃及人与以色列人。",
  "repeatedWords": [
    {
      "word": "法老",
      "count": 5
    },
    {
      "word": "埃及",
      "count": 8
    },
    {
      "word": "耶和华",
      "count": 4
    },
    {
      "word": "出去",
      "count": 4
    },
    {
      "word": "百姓",
      "count": 4
    }
  ],
  "segments": [
    {
      "title": "最后一灾与离开的预备",
      "rangeStart": 1,
      "rangeEnd": 3,
      "questions": [
        "第1节里，耶和华怎样预告这“再一样的灾殃”的结果？法老的态度会有什么变化？",
        "第2节为什么特别提到向邻舍要金器银器？这一步和“离开这地”有什么关系？",
        "第3节提到百姓在埃及人眼前蒙恩，摩西也被看为极大；这说明前面这些事件已经在埃及人心里造成了什么影响？"
      ]
    },
    {
      "title": "半夜的审判与明显的分别",
      "rangeStart": 4,
      "rangeEnd": 7,
      "questions": [
        "摩西在第4至6节怎样描述将要发生的事？哪些细节让你感受到这场灾的全面和严重？",
        "第5节从法老到婢女，再到头生的牲畜都被提到，这样的表达想强调什么？",
        "第7节说以色列中连狗也不敢向他们摇舌，这句话用很生活化的画面说明了什么？",
        "这一段最后说“耶和华是将埃及人和以色列人分别出来”，你觉得“分别”在这里具体表现在哪些方面？"
      ]
    },
    {
      "title": "摩西离开法老与结局的说明",
      "rangeStart": 8,
      "rangeEnd": 10,
      "questions": [
        "第8节里，摩西预告法老的臣仆最终会怎样来见他？这和前面法老一再强硬形成了什么对比？",
        "经文特别提到摩西“气忿忿地离开法老”，你觉得他的愤怒可能和什么有关？",
        "第9至10节怎样解释法老一直不听的原因？这里一方面有人持续拒绝，另一方面神又在做什么？",
        "读完整章，你觉得这段经文更突出的是人的顽固，还是神计划的坚定？为什么？"
      ]
    }
  ],
  "chapterLeaderHint": [
    "带领时可以先请大家观察：本章虽然短，却像最后一灾前的正式宣告，重点不在灾难过程，而在神提前说出结果。",
    "可以提醒组员留意对比：法老与以色列人、埃及人的哀号与以色列人的平安、人的不听与神话语必成就。",
    "讨论时尽量让大家先从经文找答案，例如“哪些词重复出现”“哪些画面最强烈”，再进入简短应用。",
    "如果进入应用，可以轻轻连接到生活：当人一再硬着心时，会越来越看不见神已经显明的作为。"
  ],
  "closing": "这一章让人看见，最后一灾还没发生时，耶和华已经把结果说清楚：法老终究要放人，以色列人要被分别出来，埃及却要面对沉重的哀号。神的审判不是失控的爆发，而是祂早已宣告、也必成就的行动。查考时可以思想：当神的话已经说得很清楚，人还要不要继续硬着心。",
  "title": "最后一灾前的宣告",
  "generatedAt": "2026-04-03T05:51:25.661Z",
  "savedAt": "2026-04-03T06:05:23.153Z"
}