{
  "version": "default",
  "versionLabel": "默认版",
  "contentLang": "zh",
  "bookId": "EST",
  "bookLabel": "以斯帖记",
  "chapter": 10,
  "theme": "神在历史收尾中显出治理，使被拯救的百姓因忠心领袖得着平安与益处",
  "repeatedWords": [
    {
      "word": "亚哈随鲁王",
      "count": 2
    },
    {
      "word": "末底改",
      "count": 2
    },
    {
      "word": "犹大人",
      "count": 2
    },
    {
      "word": "历史",
      "count": 1
    },
    {
      "word": "高升",
      "count": 1
    },
    {
      "word": "求好处",
      "count": 1
    },
    {
      "word": "和平",
      "count": 1
    }
  ],
  "segments": [
    {
      "title": "王权的扩展与历史的记载",
      "rangeStart": 1,
      "rangeEnd": 2,
      "questions": [
        "第1节为什么先提到亚哈随鲁王向旱地和海岛的人民征收进贡？这句话营造出怎样的历史背景？",
        "第2节提到王的权柄能力，以及末底改被抬举高升的事都写在官方历史上，这样的结尾有什么分量？",
        "从“写在玛代和波斯王的历史上”来看，作者想让读者怎样看待末底改的地位和这段经历？"
      ]
    },
    {
      "title": "末底改的地位与他的服事",
      "rangeStart": 3,
      "rangeEnd": 3,
      "questions": [
        "第3节怎样一步步描述末底改的身份和影响力？请留意他在王面前、在犹大人中间、在本族之中的位置。",
        "经文说末底改“得他众弟兄的喜悦”，这和他“为本族的人求好处，向他们说和平的话”有什么关系？",
        "末底改身居高位，却特别为本族谋益处、说和平的话，这给我们看见怎样的领导方式？",
        "联系全卷书的故事来看，以斯帖记最后用末底改作结，对当时的犹大人会带来什么安慰和盼望？"
      ]
    }
  ],
  "chapterLeaderHint": [
    "本章只有3节，适合当作全卷书的总结来带领，不必单独拉得太散。",
    "可先请组员回顾末底改在全书中的转变：被轻看、被记念、被抬举、到最后成为宰相。",
    "带领时注意让大家看见，本章重点不只是“一个人成功了”，而是他的高升带来群体的益处与平安。",
    "可以引导组员观察经文如何同时提到帝国权势与犹大群体的安稳，帮助大家思考神如何在大历史中保守自己的百姓。",
    "应用时可落在：人在位置上时，是不是只顾自己，还是会主动为身边的人求好处、说和平的话。"
  ],
  "closing": "以斯帖记的结尾很安静，却很有力量。故事没有停在危机解除，而是停在末底改被立为高位，并且继续为本族求好处。这个收尾提醒我们，神的保守不只是把人从危险中拉出来，也会继续在历史中为祂的百姓预备平安。查经结束时，可以邀请大家思想：如果神把我放在一个有影响力的位置上，我会怎样使用这个位置去祝福别人？",
  "title": "以斯帖记第10章查经：末底改的高升与群体的益处",
  "generatedAt": "2026-03-31T11:58:50.964Z",
  "savedAt": "2026-03-31T11:58:50.964Z"
}