{
  "version": "default",
  "versionLabel": "默认版",
  "contentLang": "zh",
  "bookId": "EZR",
  "bookLabel": "以斯拉记",
  "chapter": 9,
  "theme": "百姓与外邦人通婚得罪神，以斯拉因群体的失败深深忧伤，在神面前承认历史性的罪，并承认神的恩典与公义。",
  "repeatedWords": [
    {
      "word": "罪",
      "count": 10
    },
    {
      "word": "神",
      "count": 12
    },
    {
      "word": "我们",
      "count": 18
    },
    {
      "word": "命令",
      "count": 2
    },
    {
      "word": "外邦",
      "count": 2
    },
    {
      "word": "逃脱",
      "count": 3
    }
  ],
  "segments": [
    {
      "title": "百姓的混杂与领袖的责任",
      "rangeStart": 1,
      "rangeEnd": 2,
      "questions": [
        "首领向以斯拉报告的核心问题是什么？经文怎样描述这不是普通的婚姻问题，而是属灵上的败坏？",
        "第2节提到“圣洁的种类”和“混杂”，这两个词让你看见神对子民身份有什么要求？",
        "为什么经文特别指出“首领和官长在这事上为罪魁”？这对群体的影响会有多大？"
      ]
    },
    {
      "title": "以斯拉对罪的震惊与同感",
      "rangeStart": 3,
      "rangeEnd": 5,
      "questions": [
        "以斯拉听见这事后有哪些强烈反应？这些动作表达出他对罪怎样的态度？",
        "第4节说“凡为以色列神言语战兢的”都聚集过来，这些人有什么共同特点？",
        "以斯拉没有立刻处理问题，而是忧闷直到献晚祭的时候。这样的停顿可能说明了什么？"
      ]
    },
    {
      "title": "从羞愧开始的认罪",
      "rangeStart": 6,
      "rangeEnd": 7,
      "questions": [
        "以斯拉一开口为什么先说“抱愧蒙羞，不敢仰面”？这反映出他在神面前怎样的心？",
        "虽然不是以斯拉个人犯下全部的罪，他为什么一直用“我们的罪”来祷告？",
        "第7节怎样把眼前的失败和以色列从列祖以来的历史连接起来？"
      ]
    },
    {
      "title": "在审判中仍看见神的施恩",
      "rangeStart": 8,
      "rangeEnd": 9,
      "questions": [
        "第8到9节里，以斯拉数算了哪些具体的恩典？请从经文中找出来。",
        "“安稳如钉子钉在他的圣所”“光照我们的眼目”“稍微复兴”这些说法分别传递出怎样的画面？",
        "以斯拉一边说“我们是奴仆”，一边又见证神没有丢弃他们，这种张力对理解他们当时的处境有什么帮助？"
      ]
    },
    {
      "title": "明知神有命令，却再次违背",
      "rangeStart": 10,
      "rangeEnd": 12,
      "questions": [
        "第10节说“我们还有甚么话可说呢”，这句话为什么显得格外沉重？",
        "以斯拉引用先知的话时，重点强调了哪些命令和理由？",
        "从第11到12节看，神禁止与列国结亲，主要关心的是民族界线、政治利益，还是属灵圣洁？经文给了你什么依据？"
      ]
    },
    {
      "title": "承认神公义，也承认自己站立不住",
      "rangeStart": 13,
      "rangeEnd": 15,
      "questions": [
        "以斯拉怎么看过去所受的刑罚？“轻于我们罪所当得的”这句话说明他对神审判有什么认识？",
        "第14节提出“岂可再违背你的命令”，这不是单纯提问，更像什么性质的话？",
        "本章最后说“无人在你面前站立得住”，这句总结把全章带到了怎样的属灵气氛中？"
      ]
    }
  ],
  "chapterLeaderHint": [
    "带领时可先帮助组员看清本章的主要张力：一方面是严重的罪，另一方面是神已经施下的恩典。",
    "讨论通婚问题时，重点放在经文所强调的属灵混杂、可憎之事和违背神命令，不要轻易转成现代婚恋话题的泛泛讨论。",
    "可提醒组员留意以斯拉不断使用“我们”，帮助大家思想群体认罪与属灵责任，而不只是批评别人。",
    "本章几乎是一篇祷告，适合引导组员观察以斯拉祷告的结构：羞愧、回顾历史、数算恩典、承认悖逆、伏在神公义之下。",
    "应用时可以轻轻落在：我们是否对罪仍有敏感、是否会把神的恩典当作继续随便的理由、属灵领袖是否先为群体承担祷告责任。"
  ],
  "closing": "本章没有给出轻松的结尾，而是停在神的公义面前。带查经时不必急着“解决张力”，反而可以让组员停留在以斯拉的祷告里，学习怎样认真面对罪，也认真记念神的恩典。",
  "title": "以斯拉记第9章：在群体罪中俯伏认罪",
  "generatedAt": "2026-03-31T11:48:21.435Z",
  "savedAt": "2026-03-31T11:48:21.435Z"
}