{
  "version": "default",
  "versionLabel": "默认版",
  "contentLang": "zh",
  "bookId": "DEU",
  "bookLabel": "申命记",
  "chapter": 15,
  "theme": "神要求祂的百姓在金钱、人与人关系、奴仆制度和献祭生活上，活出怜悯、公义与圣洁，记念自己曾蒙拯救。",
  "repeatedWords": [
    {
      "word": "弟兄",
      "count": 8
    },
    {
      "word": "耶和华你的神",
      "count": 10
    },
    {
      "word": "赐福",
      "count": 4
    },
    {
      "word": "豁免",
      "count": 4
    },
    {
      "word": "给",
      "count": 6
    },
    {
      "word": "自由",
      "count": 3
    }
  ],
  "segments": [
    {
      "title": "豁免年的原则：在神的百姓中学习松手",
      "rangeStart": 1,
      "rangeEnd": 6,
      "questions": [
        "1-3节怎样说明“豁免”的具体做法？这项安排主要是针对谁，又保留了什么界线？",
        "4-6节一面说“你们中间没有穷人”，11节却又说“穷人永不断绝”。从这一段看，这两句话分别强调什么？",
        "这段经文把“听从神的话”和“经济生活中的祝福”连在一起，你觉得神想塑造一个怎样的群体？"
      ]
    },
    {
      "title": "面对穷乏的弟兄：不要忍心，也不要算计",
      "rangeStart": 7,
      "rangeEnd": 11,
      "questions": [
        "7-8节用了哪些很具体的动作和态度来描述帮助穷人的方式？哪些词最打动你？",
        "9节特别提醒人防备什么“恶念”？为什么豁免年快到时，人更容易不肯借给别人？",
        "10节不只要求“给”，还要求“心里不可愁烦”。神为什么连给人的态度也这么看重？",
        "11节承认穷人不会断绝，这对以色列人持续关心困苦人有什么提醒？对我们今天的小组生活有什么直接启发？"
      ]
    },
    {
      "title": "释放希伯来奴仆：自由不是打发，而是成全",
      "rangeStart": 12,
      "rangeEnd": 18,
      "questions": [
        "12-14节规定奴仆第七年离开时，不可“空手而去”。这显示神关心的只是释放本身，还是也关心他离开后的生活？",
        "15节为什么要以“你在埃及地作过奴仆”为理由？过去被救赎的经历，怎样成为今天善待别人的动力？",
        "16-17节提到奴仆若因爱主人而自愿留下，就用刺耳朵的方式立约。这个安排反映出主仆关系已经不只是交易，还包含什么？",
        "18节为什么特别说“不可看为难事”？从人的现实计算和神应许的赐福来看，这节经文在纠正什么心态？"
      ]
    },
    {
      "title": "头生的归主：分别为圣，也要按规矩献上",
      "rangeStart": 19,
      "rangeEnd": 23,
      "questions": [
        "19节为什么连“不可用它耕地”“不可剪毛”都说得这么细？这怎样帮助人明白“分别为圣”不是口头上的？",
        "20节提到一家人每年在耶和华面前吃这头生的，这种做法除了献祭之外，也表达了怎样的敬拜生活？",
        "21-22节为什么有残疾的头生牲畜不能献给耶和华，却仍可以在城里当普通食物吃？这让我们看见神对献上的要求是什么？",
        "23节再次强调不可吃血。放在本段结尾，这条规定是在提醒百姓对生命和圣物保持怎样的态度？"
      ]
    }
  ],
  "chapterLeaderHint": [
    "带领时可先请组员观察本章重复出现的词，如“弟兄”“给”“赐福”“耶和华你的神”，帮助大家看到本章把敬虔、金钱和群体生活连在一起。",
    "本章可按四段推进：豁免债务、帮助穷人、释放奴仆、献上头生。每段都可先问“神吩咐什么”，再问“神为什么这样吩咐”。",
    "讨论7-11节和12-18节时，可特别留意“手”和“心”的描写：不只是行为上帮助，也包括内心不冷漠、不算计、不勉强。",
    "带领者可提醒组员，本章不是抽象的慈善原则，而是神要祂的子民在具体经济关系中活出恩典、公义和记念救赎。",
    "若进入应用，可请大家从经文出发思考：我们会不会因为怕吃亏而不愿松手？会不会在帮助人时外面给了，里面却不甘心？",
    "结束时可以总结：本章不是单讲“施舍”，而是在说一个蒙神赐福、记念神救赎的群体，应该怎样对待弟兄、资源和献给神之物。"
  ],
  "closing": "申命记15章让人看见，神所要的不是表面守规矩，而是一个肯松手、记念恩典、尊重圣洁的群体。无论是债务、穷人、奴仆，还是头生的牲畜，神都在训练祂的百姓：既然你们是被我救赎、被我赐福的人，就不要抓得太紧，也不要献得太随便，而要在生活中活出怜悯、公义和敬畏。",
  "title": "申命记第15章｜豁免、慷慨与分别为圣",
  "generatedAt": "2026-03-31T09:49:33.288Z",
  "savedAt": "2026-03-31T09:49:33.288Z"
}