{
  "version": "default",
  "versionLabel": "默认版",
  "contentLang": "zh",
  "bookId": "PSA",
  "bookLabel": "诗篇",
  "chapter": 138,
  "theme": "大卫在称谢、祷告与盼望中承认：耶和华信实回应人的呼求，也必在患难中成全祂的作为。",
  "repeatedWords": [
    {
      "word": "耶和华",
      "count": 6
    },
    {
      "word": "称谢",
      "count": 3
    },
    {
      "word": "慈爱",
      "count": 2
    },
    {
      "word": "歌颂",
      "count": 2
    },
    {
      "word": "你",
      "count": 17
    }
  ],
  "segments": [
    {
      "title": "一心称谢：因神的慈爱、诚实与回应",
      "rangeStart": 1,
      "rangeEnd": 3,
      "questions": [
        "第1节里，大卫说“我要一心称谢你”，这种“专心”的态度和一般口头感谢有什么不同？",
        "第1-2节中，大卫具体因什么来称赞神的名？“慈爱”“诚实”“你的话”分别让你看到神怎样的性情？",
        "第3节提到神怎样回应大卫的呼求？这里不仅有“应允”，还有哪一种内在的帮助？",
        "从1-3节看，大卫的赞美不是空泛的，而是建立在什么经历之上？"
      ]
    },
    {
      "title": "从个人经历到万王颂赞",
      "rangeStart": 4,
      "rangeEnd": 6,
      "questions": [
        "第4节为什么说“地上的君王都要称谢你”？经文把这种称谢和什么联系在一起？",
        "第5节里，君王歌颂的是耶和华的什么？这和前面“听见了你口中的言语”有什么关系？",
        "第6节怎样同时描写神的“高”和祂对人的态度？这对我们理解神的伟大有什么提醒？",
        "经文说神“看顾低微的人”，却“从远处看出骄傲的人”，这两种人形成了怎样鲜明的对比？"
      ]
    },
    {
      "title": "患难中的把握：神必救我，也必成全",
      "rangeStart": 7,
      "rangeEnd": 8,
      "questions": [
        "第7节里，大卫身处什么处境？他对神将要怎样介入有哪几层确信？",
        "“你必将我救活”“你必伸手抵挡他们”“你的右手也必救我”这些表达，怎样一步步加强了大卫的信心？",
        "第8节“耶和华必成全关乎我的事”说明大卫对自己的人生有什么认识？",
        "这首诗最后以“求你不要离弃你手所造的”结束，一边是确信，一边是祈求，这样的祷告给我们什么启发？"
      ]
    }
  ],
  "chapterLeaderHint": [
    "可以先请大家观察本篇情绪的推进：从个人称谢，扩展到列王称谢，最后落到个人患难中的祷告与把握。",
    "带领时可鼓励组员多从动词入手，如“称谢、歌颂、呼求、应允、看顾、救活、成全”，帮助大家抓住诗篇的行动线索。",
    "第2节“你的话显为大”可邀请组员分享不同译法带来的理解，但重点仍放在神话语的可靠与尊荣上。",
    "讨论第6节时，可引导大家留意神的伟大不是冷漠的高高在上，而是能看顾低微、识破骄傲。",
    "最后一段适合结合生活处境分享，但要尽量回到经文本身：大卫的信心不是没有患难，而是在患难中仍认定神会介入。"
  ],
  "closing": "这篇诗让我们看见，真实的赞美常常来自真实的经历：神听祷告、加力量、看顾卑微的人，也在患难中施行拯救。带领小组结束时，可以邀请大家用一句话回应：在这段经文里，你最想抓住神哪一方面的应许或性情？",
  "title": "诗篇138章查经：在高处掌权的主，仍看顾卑微的人",
  "generatedAt": "2026-03-31T13:15:36.695Z",
  "savedAt": "2026-03-31T13:15:36.695Z"
}